setup.py
raven_cron/__init__.py
raven_cron/runner.py
raven_cron/version.py
raven_cron.egg-info/PKG-INFO
raven_cron.egg-info/SOURCES.txt
raven_cron.egg-info/dependency_links.txt
raven_cron.egg-info/entry_points.txt
raven_cron.egg-info/requires.txt
raven_cron.egg-info/top_level.txt