Metadata-Version: 1.1
Name: raven-cron
Version: 0.1.0
Summary: Raven-cron is a command-line wrapper that reports unsuccessful runs to Sentry (https://www.getsentry.com)
Home-page: http://github.com/mediacore/raven-cron
Author: Jonas Pfenniger
Author-email: zimbatm@zimbatm.com
License: MIT
Platform: UNKNOWN
Classifier: Topic :: Utilities
Classifier: Intended Audience :: System Administrators
Classifier: Operating System :: OS Independent
Classifier: License :: OSI Approved :: MIT License
